{
  "domains": [
    {
      "thumbnailImage": "/assets/images/domain1-thumbnail.jpg",
      "domainName": "example.com",
      "domainStatus": "active",
      "domainProvider": "GoDaddy",
      "expirationDate": "2026-05-16",
      "firstName": "James",
      "lastName": "Carter",
      "streetAddress": "482 Elm Street",
      "city": "Austin",
      "state": "TX",
      "zip": "73301",
      "phone": "+1 (512) 555-0147",
      "email": "james.carter@example.com",
      "billing": {
        "firstName": "James",
        "lastName": "Carter",
        "streetAddress": "482 Elm Street",
        "city": "Austin",
        "state": "TX",
        "zip": "73301",
        "country": "United States",
        "creditCard": "4532 8910 1456 3789"
      },
      "customDnsRecords": [
        { "host": "www", "type": "CNAME", "priority": "N/A", "ttl": "4 hrs", "data": "ext-sq.squarespace.com" },
        { "host": "mail", "type": "CNAME", "priority": "N/A", "ttl": "1 hr", "data": "ghs.googlehosted.com" },
        { "host": "@", "type": "MX", "priority": "1", "ttl": "4 hrs", "data": "aspmx.l.google.com" },
        { "host": "@", "type": "MX", "priority": "5", "ttl": "4 hrs", "data": "alt1.aspmx.l.google.com" },
        { "host": "@", "type": "TXT", "priority": "N/A", "ttl": "1 hr", "data": "v=spf1 include:_spf.google.com ~all" },
        { "host": "blog", "type": "CNAME", "priority": "N/A", "ttl": "4 hrs", "data": "hosting.ghost.io" }
      ]
    },
    {
      "thumbnailImage": "/assets/images/domain2-thumbnail.jpg",
      "domainName": "mysite.net",
      "domainStatus": "pending-renewal",
      "domainProvider": "Namecheap",
      "expirationDate": "2025-08-23",
      "firstName": "Priya",
      "lastName": "Menon",
      "streetAddress": "1200 Market Street, Suite 300",
      "city": "San Francisco",
      "state": "CA",
      "zip": "94103",
      "phone": "+1 (415) 555-0293",
      "email": "priya.menon@mysite.net",
      "billing": {
        "firstName": "Priya",
        "lastName": "Menon",
        "streetAddress": "1200 Market Street, Suite 300",
        "city": "San Francisco",
        "state": "CA",
        "zip": "94103",
        "country": "United States",
        "creditCard": "5214 6378 9021 4453"
      }
    },
    {
      "thumbnailImage": "/assets/images/domain3-thumbnail.jpg",
      "domainName": "pixelperfect.design",
      "domainStatus": "active",
      "domainProvider": "Squarespace",
      "expirationDate": "2027-02-26",
      "firstName": "Elena",
      "lastName": "Rossi",
      "streetAddress": "37 Magnolia Avenue",
      "city": "Portland",
      "state": "OR",
      "zip": "97201",
      "phone": "+1 (503) 555-0182",
      "email": "elena.rossi@pixelperfect.design",
      "billing": {
        "firstName": "Elena",
        "lastName": "Rossi",
        "streetAddress": "37 Magnolia Avenue",
        "city": "Portland",
        "state": "OR",
        "zip": "97201",
        "country": "United States",
        "creditCard": "3782 412093 56721"
      },
      "customDnsRecords": [
        { "host": "www", "type": "CNAME", "priority": "N/A", "ttl": "4 hrs", "data": "ext-sq.squarespace.com" },
        { "host": "@", "type": "TXT", "priority": "N/A", "ttl": "1 hr", "data": "google-site-verification=a1b2c3d4e5f6g7h8i9" },
        { "host": "_dmarc", "type": "TXT", "priority": "N/A", "ttl": "4 hrs", "data": "v=DMARC1; p=quarantine; rua=mailto:dmarc@pixelperfect.design" },
        { "host": "portfolio", "type": "A", "priority": "N/A", "ttl": "1 hr", "data": "76.76.21.21" },
        { "host": "shop", "type": "CNAME", "priority": "N/A", "ttl": "4 hrs", "data": "shops.myshopify.com" }
      ]
    },
    {
      "thumbnailImage": "/assets/images/domain4-thumbnail.jpg",
      "domainName": "acmewidgets.io",
      "domainStatus": "active",
      "domainProvider": "Cloudflare",
      "expirationDate": "2026-11-05",
      "firstName": "Marcus",
      "lastName": "Chen",
      "streetAddress": "901 Innovation Drive",
      "city": "Seattle",
      "state": "WA",
      "zip": "98101",
      "phone": "+1 (206) 555-0364",
      "email": "marcus.chen@acmewidgets.io",
      "billing": {
        "firstName": "Marcus",
        "lastName": "Chen",
        "streetAddress": "901 Innovation Drive",
        "city": "Seattle",
        "state": "WA",
        "zip": "98101",
        "country": "United States",
        "creditCard": "4716 0234 5678 9102"
      },
      "customDnsRecords": [
        { "host": "www", "type": "CNAME", "priority": "N/A", "ttl": "4 hrs", "data": "ext-sq.squarespace.com" },
        { "host": "api", "type": "A", "priority": "N/A", "ttl": "30 min", "data": "34.120.54.55" },
        { "host": "staging", "type": "A", "priority": "N/A", "ttl": "30 min", "data": "34.120.54.60" },
        { "host": "@", "type": "MX", "priority": "10", "ttl": "4 hrs", "data": "mx1.forwardemail.net" },
        { "host": "@", "type": "MX", "priority": "20", "ttl": "4 hrs", "data": "mx2.forwardemail.net" },
        { "host": "@", "type": "TXT", "priority": "N/A", "ttl": "1 hr", "data": "v=spf1 a mx include:forwardemail.net ~all" },
        { "host": "_acme-challenge", "type": "TXT", "priority": "N/A", "ttl": "30 min", "data": "dGVzdC12YWxpZGF0aW9uLXRva2Vu" }
      ]
    },
    {
      "thumbnailImage": "/assets/images/domain5-thumbnail.jpg",
      "domainName": "coastalbakery.com",
      "domainStatus": "pending-renewal",
      "domainProvider": "Squarespace",
      "expirationDate": "2025-12-14",
      "firstName": "Sofia",
      "lastName": "Ramirez",
      "streetAddress": "225 Ocean Boulevard",
      "city": "Santa Monica",
      "state": "CA",
      "zip": "90401",
      "phone": "+1 (310) 555-0418",
      "email": "sofia.ramirez@coastalbakery.com",
      "billing": {
        "firstName": "Sofia",
        "lastName": "Ramirez",
        "streetAddress": "225 Ocean Boulevard",
        "city": "Santa Monica",
        "state": "CA",
        "zip": "90401",
        "country": "United States",
        "creditCard": "5389 2104 7763 8821"
      }
    },
    {
      "thumbnailImage": "/assets/images/domain6-thumbnail.jpg",
      "domainName": "northstar.studio",
      "domainStatus": "active",
      "domainProvider": "Google Domains",
      "expirationDate": "2026-04-09",
      "firstName": "Owen",
      "lastName": "Fitzgerald",
      "streetAddress": "58 Pine Ridge Road",
      "city": "Denver",
      "state": "CO",
      "zip": "80202",
      "phone": "+1 (720) 555-0531",
      "email": "owen.fitzgerald@northstar.studio",
      "billing": {
        "firstName": "Owen",
        "lastName": "Fitzgerald",
        "streetAddress": "58 Pine Ridge Road",
        "city": "Denver",
        "state": "CO",
        "zip": "80202",
        "country": "United States",
        "creditCard": "6011 4523 8901 2345"
      }
    },
    {
      "thumbnailImage": "/assets/images/domain7-thumbnail.jpg",
      "domainName": "wanderlust.travel",
      "domainStatus": "active",
      "domainProvider": "Hover",
      "expirationDate": "2027-01-30",
      "firstName": "Amara",
      "lastName": "Okafor",
      "streetAddress": "3400 Peachtree Lane NE",
      "city": "Atlanta",
      "state": "GA",
      "zip": "30305",
      "phone": "+1 (404) 555-0672",
      "email": "amara.okafor@wanderlust.travel",
      "billing": {
        "firstName": "Amara",
        "lastName": "Okafor",
        "streetAddress": "3400 Peachtree Lane NE",
        "city": "Atlanta",
        "state": "GA",
        "zip": "30305",
        "country": "United States",
        "creditCard": "4929 7381 0256 4490"
      },
      "customDnsRecords": [
        { "host": "www", "type": "CNAME", "priority": "N/A", "ttl": "4 hrs", "data": "ext-sq.squarespace.com" },
        { "host": "booking", "type": "CNAME", "priority": "N/A", "ttl": "1 hr", "data": "cname.vercel-dns.com" },
        { "host": "@", "type": "MX", "priority": "1", "ttl": "4 hrs", "data": "aspmx.l.google.com" },
        { "host": "@", "type": "MX", "priority": "5", "ttl": "4 hrs", "data": "alt1.aspmx.l.google.com" },
        { "host": "@", "type": "MX", "priority": "10", "ttl": "4 hrs", "data": "alt2.aspmx.l.google.com" },
        { "host": "@", "type": "TXT", "priority": "N/A", "ttl": "1 hr", "data": "v=spf1 include:_spf.google.com ~all" }
      ]
    },
    {
      "thumbnailImage": "/assets/images/domain8-thumbnail.jpg",
      "domainName": "greensprout.org",
      "domainStatus": "active",
      "domainProvider": "Namecheap",
      "expirationDate": "2026-08-01",
      "firstName": "Liam",
      "lastName": "Nakamura",
      "streetAddress": "712 Birchwood Terrace",
      "city": "Minneapolis",
      "state": "MN",
      "zip": "55401",
      "phone": "+1 (612) 555-0789",
      "email": "liam.nakamura@greensprout.org",
      "billing": {
        "firstName": "Liam",
        "lastName": "Nakamura",
        "streetAddress": "712 Birchwood Terrace",
        "city": "Minneapolis",
        "state": "MN",
        "zip": "55401",
        "country": "United States",
        "creditCard": "5102 6834 9017 2256"
      }
    },
    {
      "thumbnailImage": "/assets/images/domain9-thumbnail.jpg",
      "domainName": "rivervalleyfarm.co",
      "domainStatus": "pending-renewal",
      "domainProvider": "GoDaddy",
      "expirationDate": "2025-09-18",
      "firstName": "Hannah",
      "lastName": "Whitfield",
      "streetAddress": "1045 County Road 12",
      "city": "Charlottesville",
      "state": "VA",
      "zip": "22901",
      "phone": "+1 (434) 555-0856",
      "email": "hannah.whitfield@rivervalleyfarm.co",
      "billing": {
        "firstName": "Hannah",
        "lastName": "Whitfield",
        "streetAddress": "1045 County Road 12",
        "city": "Charlottesville",
        "state": "VA",
        "zip": "22901",
        "country": "United States",
        "creditCard": "3714 496210 83947"
      }
    },
    {
      "thumbnailImage": "/assets/images/domain10-thumbnail.jpg",
      "domainName": "blueoak.dev",
      "domainStatus": "active",
      "domainProvider": "Cloudflare",
      "expirationDate": "2026-03-22",
      "firstName": "Daniel",
      "lastName": "Park",
      "streetAddress": "289 Congress Avenue, Unit 4B",
      "city": "Boston",
      "state": "MA",
      "zip": "02210",
      "phone": "+1 (617) 555-0943",
      "email": "daniel.park@blueoak.dev",
      "billing": {
        "firstName": "Daniel",
        "lastName": "Park",
        "streetAddress": "289 Congress Avenue, Unit 4B",
        "city": "Boston",
        "state": "MA",
        "zip": "02210",
        "country": "United States",
        "creditCard": "4485 1672 3098 5541"
      },
      "customDnsRecords": [
        { "host": "www", "type": "CNAME", "priority": "N/A", "ttl": "4 hrs", "data": "ext-sq.squarespace.com" },
        { "host": "docs", "type": "CNAME", "priority": "N/A", "ttl": "1 hr", "data": "cname.vercel-dns.com" },
        { "host": "status", "type": "CNAME", "priority": "N/A", "ttl": "1 hr", "data": "statuspage.betteruptime.com" },
        { "host": "@", "type": "TXT", "priority": "N/A", "ttl": "4 hrs", "data": "v=spf1 include:mailgun.org ~all" },
        { "host": "k1._domainkey", "type": "CNAME", "priority": "N/A", "ttl": "4 hrs", "data": "dkim.mailgun.org" }
      ]
    },
    {
      "thumbnailImage": "/assets/images/domain11-thumbnail.jpg",
      "domainName": "artisanmart.shop",
      "domainStatus": "active",
      "domainProvider": "Squarespace",
      "expirationDate": "2026-10-07",
      "firstName": "Isla",
      "lastName": "Brennan",
      "streetAddress": "560 Main Street",
      "city": "Nashville",
      "state": "TN",
      "zip": "37201",
      "phone": "+1 (615) 555-0117",
      "email": "isla.brennan@artisanmart.shop",
      "billing": {
        "firstName": "Isla",
        "lastName": "Brennan",
        "streetAddress": "560 Main Street",
        "city": "Nashville",
        "state": "TN",
        "zip": "37201",
        "country": "United States",
        "creditCard": "5267 9043 1185 6672"
      }
    },
    {
      "thumbnailImage": "/assets/images/domain12-thumbnail.jpg",
      "domainName": "evergreenphotography.us",
      "domainStatus": "active",
      "domainProvider": "Bluehost",
      "expirationDate": "2027-06-12",
      "firstName": "Victor",
      "lastName": "Johansson",
      "streetAddress": "1833 Lakeview Drive",
      "city": "Chicago",
      "state": "IL",
      "zip": "60614",
      "phone": "+1 (312) 555-0258",
      "email": "victor.johansson@evergreenphotography.us",
      "billing": {
        "firstName": "Victor",
        "lastName": "Johansson",
        "streetAddress": "1833 Lakeview Drive",
        "city": "Chicago",
        "state": "IL",
        "zip": "60614",
        "country": "United States",
        "creditCard": "6011 8823 4567 0198"
      },
      "customDnsRecords": [
        { "host": "www", "type": "CNAME", "priority": "N/A", "ttl": "4 hrs", "data": "ext-sq.squarespace.com" },
        { "host": "gallery", "type": "A", "priority": "N/A", "ttl": "1 hr", "data": "151.101.1.195" },
        { "host": "@", "type": "MX", "priority": "10", "ttl": "4 hrs", "data": "in1-smtp.messagingengine.com" },
        { "host": "@", "type": "MX", "priority": "20", "ttl": "4 hrs", "data": "in2-smtp.messagingengine.com" },
        { "host": "@", "type": "TXT", "priority": "N/A", "ttl": "1 hr", "data": "v=spf1 include:messagingengine.com ~all" },
        { "host": "fm1._domainkey", "type": "CNAME", "priority": "N/A", "ttl": "4 hrs", "data": "fm1.evergreenphotography.us.dkim.fmhosted.com" },
        { "host": "fm2._domainkey", "type": "CNAME", "priority": "N/A", "ttl": "4 hrs", "data": "fm2.evergreenphotography.us.dkim.fmhosted.com" }
      ]
    }
  ]
}
